brukerapi/__init__.py
brukerapi/cli.py
brukerapi/data.py
brukerapi/dataset.py
brukerapi/exceptions.py
brukerapi/folders.py
brukerapi/jcampdx.py
brukerapi/mergers.py
brukerapi/schemas.py
brukerapi/splitters.py
brukerapi/utils.py
brukerapi/config/properties_2dseq_core.json
brukerapi/config/properties_2dseq_custom.json
brukerapi/config/properties_fid_core.json
brukerapi/config/properties_fid_custom.json
brukerapi/config/properties_rawdata_core.json
brukerapi/config/properties_rawdata_custom.json
brukerapi/config/properties_traj_core.json
brukerapi/config/properties_traj_custom.json
brukerapi-0.1.10.dist-info/licenses/LICENSE
brukerapi-0.1.10.dist-info/METADATA
brukerapi-0.1.10.dist-info/WHEEL
brukerapi-0.1.10.dist-info/entry_points.txt
brukerapi-0.1.10.dist-info/top_level.txt
brukerapi-0.1.10.dist-info/RECORD
