Metadata-Version: 2.4
Name: brukerapi
Version: 0.1.10
Summary: Bruker API
Author-email: Tomas Psorn <tomaspsorn@isibrno.cz>
License: MIT
Project-URL: Homepage, https://github.com/isi-nmr/brukerapi-python
Project-URL: Download, https://github.com/isi-nmr/brukerapi-python/releases/latest
Requires-Python: >=3.8
License-File: LICENSE
Requires-Dist: numpy<2; python_version < "3.9"
Requires-Dist: numpy>=1.26.0; python_version >= "3.9"
Requires-Dist: pyyaml
Provides-Extra: dev
Requires-Dist: pytest; extra == "dev"
Requires-Dist: zenodo_get; extra == "dev"
Dynamic: license-file
